[
  {
    "_iconSource": 0,
    "_title": null,
    "Name": "OfficeAutomateTools",
    "Code": "650002",
    "CommandType": 6,
    "QualifiedName": "Tosan.Modern.Boursar.UI.GeneralCommand,Tosan.Modern.Boursar.UI",
    "PresenterName": null,
    "DefaultFilterQualifiedName": null,
    "IconName": null,
    "ObjectDefinition": null,
    "ModuleId": 67,
    "DisplayState": 0,
    "TransactionCode": null,
    "IsParametric": false,
    "ParentFilter": null,
    "ID": 650002,
    "Version": 0,
    "CreationDate": "2020-04-05T12:12:00.2359358+04:30",
    "LastChange": "2020-04-05T12:12:00.2359358+04:30",
    "Creator": "",
    "LastUpdater": ""
  },
  {
    "_iconSource": 0,
    "_title": null,
    "Name": "ConfigExchange",
    "Code": "650001",
    "CommandType": 6,
    "QualifiedName": "Tosan.Modern.Boursar.UI.GeneralCommand,Tosan.Modern.Boursar.UI",
    "PresenterName": null,
    "DefaultFilterQualifiedName": null,
    "IconName": null,
    "ObjectDefinition": null,
    "ModuleId": 67,
    "DisplayState": 0,
    "TransactionCode": null,
    "IsParametric": false,
    "ParentFilter": null,
    "ID": 650001,
    "Version": 0,
    "CreationDate": "2020-04-05T12:12:00.2359358+04:30",
    "LastChange": "2020-04-05T12:12:00.2359358+04:30",
    "Creator": "",
    "LastUpdater": ""
  },
  {
    "_iconSource": 0,
    "_title": null,
    "Name": "ConfigExchange",
    "Code": "650001",
    "CommandType": 6,
    "QualifiedName": "Tosan.Modern.Boursar.UI.GeneralCommand,Tosan.Modern.Boursar.UI",
    "PresenterName": null,
    "DefaultFilterQualifiedName": null,
    "IconName": null,
    "ObjectDefinition": null,
    "ModuleId": 67,
    "DisplayState": 0,
    "TransactionCode": null,
    "IsParametric": false,
    "ParentFilter": null,
    "ID": 650001,
    "Version": 0,
    "CreationDate": "2020-04-05T12:12:00.2359358+04:30",
    "LastChange": "2020-04-05T12:12:00.2359358+04:30",
    "Creator": "",
    "LastUpdater": ""
  },
  {
    "_iconSource": 0,
    "_title": null,
    "Name": "OfficeAutomateTools",
    "Code": "650002",
    "CommandType": 6,
    "QualifiedName": "Tosan.Modern.Boursar.UI.GeneralCommand,Tosan.Modern.Boursar.UI",
    "PresenterName": null,
    "DefaultFilterQualifiedName": null,
    "IconName": null,
    "ObjectDefinition": null,
    "ModuleId": 67,
    "DisplayState": 0,
    "TransactionCode": null,
    "IsParametric": false,
    "ParentFilter": null,
    "ID": 650002,
    "Version": 0,
    "CreationDate": "2020-04-05T12:12:00.2359358+04:30",
    "LastChange": "2020-04-05T12:12:00.2359358+04:30",
    "Creator": "",
    "LastUpdater": ""
  },
  {
    "_iconSource": 0,
    "_title": null,
    "Name": "Exchanges",
    "Code": "650005",
    "CommandType": 6,
    "QualifiedName": "Tosan.Modern.Boursar.UI.GeneralCommand,Tosan.Modern.Boursar.UI",
    "PresenterName": null,
    "DefaultFilterQualifiedName": null,
    "IconName": null,
    "ObjectDefinition": null,
    "ModuleId": 67,
    "DisplayState": 0,
    "TransactionCode": null,
    "IsParametric": false,
    "ParentFilter": null,
    "ID": 650005,
    "Version": 0,
    "CreationDate": "2020-04-05T12:12:00.2359358+04:30",
    "LastChange": "2020-04-05T12:12:00.2359358+04:30",
    "Creator": "",
    "LastUpdater": ""
  },
  {
    "_iconSource": 0,
    "_title": null,
    "Name": "Brokers",
    "Code": "650004",
    "CommandType": 6,
    "QualifiedName": "Tosan.Modern.Boursar.UI.GeneralCommand,Tosan.Modern.Boursar.UI",
    "PresenterName": null,
    "DefaultFilterQualifiedName": null,
    "IconName": null,
    "ObjectDefinition": null,
    "ModuleId": 67,
    "DisplayState": 0,
    "TransactionCode": null,
    "IsParametric": false,
    "ParentFilter": null,
    "ID": 650004,
    "Version": 0,
    "CreationDate": "2020-04-05T12:12:00.2359358+04:30",
    "LastChange": "2020-04-05T12:12:00.2359358+04:30",
    "Creator": "",
    "LastUpdater": ""
  },
  {
    "_iconSource": 0,
    "_title": null,
    "Name": "UserSearch",
    "Code": "650003",
    "CommandType": 6,
    "QualifiedName": "Tosan.Modern.Boursar.UI.GeneralCommand,Tosan.Modern.Boursar.UI",
    "PresenterName": null,
    "DefaultFilterQualifiedName": null,
    "IconName": null,
    "ObjectDefinition": null,
    "ModuleId": 67,
    "DisplayState": 0,
    "TransactionCode": null,
    "IsParametric": false,
    "ParentFilter": null,
    "ID": 650003,
    "Version": 0,
    "CreationDate": "2020-04-05T12:12:00.2359358+04:30",
    "LastChange": "2020-04-05T12:12:00.2359358+04:30",
    "Creator": "",
    "LastUpdater": ""
  },
  {
    "_iconSource": 0,
    "_title": null,
    "Name": "Brokers",
    "Code": "650004",
    "CommandType": 6,
    "QualifiedName": "Tosan.Modern.Boursar.UI.GeneralCommand,Tosan.Modern.Boursar.UI",
    "PresenterName": null,
    "DefaultFilterQualifiedName": null,
    "IconName": null,
    "ObjectDefinition": null,
    "ModuleId": 67,
    "DisplayState": 0,
    "TransactionCode": null,
    "IsParametric": false,
    "ParentFilter": null,
    "ID": 650004,
    "Version": 0,
    "CreationDate": "2020-04-05T12:12:00.2359358+04:30",
    "LastChange": "2020-04-05T12:12:00.2359358+04:30",
    "Creator": "",
    "LastUpdater": ""
  },
  {
    "_iconSource": 0,
    "_title": null,
    "Name": "UserSearch",
    "Code": "650003",
    "CommandType": 6,
    "QualifiedName": "Tosan.Modern.Boursar.UI.GeneralCommand,Tosan.Modern.Boursar.UI",
    "PresenterName": null,
    "DefaultFilterQualifiedName": null,
    "IconName": null,
    "ObjectDefinition": null,
    "ModuleId": 67,
    "DisplayState": 0,
    "TransactionCode": null,
    "IsParametric": false,
    "ParentFilter": null,
    "ID": 650003,
    "Version": 0,
    "CreationDate": "2020-04-05T12:12:00.2359358+04:30",
    "LastChange": "2020-04-05T12:12:00.2359358+04:30",
    "Creator": "",
    "LastUpdater": ""
  },
  {
    "_iconSource": 0,
    "_title": null,
    "Name": "Exchanges",
    "Code": "650005",
    "CommandType": 6,
    "QualifiedName": "Tosan.Modern.Boursar.UI.GeneralCommand,Tosan.Modern.Boursar.UI",
    "PresenterName": null,
    "DefaultFilterQualifiedName": null,
    "IconName": null,
    "ObjectDefinition": null,
    "ModuleId": 67,
    "DisplayState": 0,
    "TransactionCode": null,
    "IsParametric": false,
    "ParentFilter": null,
    "ID": 650005,
    "Version": 0,
    "CreationDate": "2020-04-05T12:12:00.2359358+04:30",
    "LastChange": "2020-04-05T12:12:00.2359358+04:30",
    "Creator": "",
    "LastUpdater": ""
  },
  {
    "_iconSource": 0,
    "_title": null,
    "Name": "Brokers",
    "Code": "650004",
    "CommandType": 6,
    "QualifiedName": "Tosan.Modern.Boursar.UI.GeneralCommand,Tosan.Modern.Boursar.UI",
    "PresenterName": null,
    "DefaultFilterQualifiedName": null,
    "IconName": null,
    "ObjectDefinition": null,
    "ModuleId": 67,
    "DisplayState": 0,
    "TransactionCode": null,
    "IsParametric": false,
    "ParentFilter": null,
    "ID": 650004,
    "Version": 0,
    "CreationDate": "2020-04-05T12:12:00.2359358+04:30",
    "LastChange": "2020-04-05T12:12:00.2359358+04:30",
    "Creator": "",
    "LastUpdater": ""
  },
  {
    "_iconSource": 0,
    "_title": null,
    "Name": "ExchangeContract",
    "Code": "650006",
    "CommandType": 6,
    "QualifiedName": "Tosan.Modern.Boursar.UI.GeneralCommand,Tosan.Modern.Boursar.UI",
    "PresenterName": null,
    "DefaultFilterQualifiedName": null,
    "IconName": null,
    "ObjectDefinition": null,
    "ModuleId": 67,
    "DisplayState": 0,
    "TransactionCode": null,
    "IsParametric": false,
    "ParentFilter": null,
    "ID": 650006,
    "Version": 0,
    "CreationDate": "2020-04-05T12:12:00.2359358+04:30",
    "LastChange": "2020-04-05T12:12:00.2359358+04:30",
    "Creator": "",
    "LastUpdater": ""
  },
  {
    "_iconSource": 0,
    "_title": null,
    "Name": "MonitoringUserTrackerStatisticReport",
    "Code": "650012",
    "CommandType": 6,
    "QualifiedName": "Tosan.Modern.Boursar.UI.GeneralCommand,Tosan.Modern.Boursar.UI",
    "PresenterName": null,
    "DefaultFilterQualifiedName": null,
    "IconName": null,
    "ObjectDefinition": null,
    "ModuleId": 67,
    "DisplayState": 0,
    "TransactionCode": null,
    "IsParametric": false,
    "ParentFilter": null,
    "ID": 650012,
    "Version": 0,
    "CreationDate": "2020-04-05T12:12:00.2359358+04:30",
    "LastChange": "2020-04-05T12:12:00.2359358+04:30",
    "Creator": "",
    "LastUpdater": ""
  },
  {
    "_iconSource": 0,
    "_title": null,
    "Name": "MonitoringUserTrackerReport",
    "Code": "650011",
    "CommandType": 6,
    "QualifiedName": "Tosan.Modern.Boursar.UI.GeneralCommand,Tosan.Modern.Boursar.UI",
    "PresenterName": null,
    "DefaultFilterQualifiedName": null,
    "IconName": null,
    "ObjectDefinition": null,
    "ModuleId": 67,
    "DisplayState": 0,
    "TransactionCode": null,
    "IsParametric": false,
    "ParentFilter": null,
    "ID": 650011,
    "Version": 0,
    "CreationDate": "2020-04-05T12:12:00.2359358+04:30",
    "LastChange": "2020-04-05T12:12:00.2359358+04:30",
    "Creator": "",
    "LastUpdater": ""
  },
  {
    "_iconSource": 0,
    "_title": null,
    "Name": "GetUsersNotUsedFromExchangeReport",
    "Code": "650010",
    "CommandType": 6,
    "QualifiedName": "Tosan.Modern.Boursar.UI.GeneralCommand,Tosan.Modern.Boursar.UI",
    "PresenterName": null,
    "DefaultFilterQualifiedName": null,
    "IconName": null,
    "ObjectDefinition": null,
    "ModuleId": 67,
    "DisplayState": 0,
    "TransactionCode": null,
    "IsParametric": false,
    "ParentFilter": null,
    "ID": 650010,
    "Version": 0,
    "CreationDate": "2020-04-05T12:12:00.2359358+04:30",
    "LastChange": "2020-04-05T12:12:00.2359358+04:30",
    "Creator": "",
    "LastUpdater": ""
  },
  {
    "_iconSource": 0,
    "_title": null,
    "Name": "CustomerExchangeTransaction",
    "Code": "650009",
    "CommandType": 6,
    "QualifiedName": "Tosan.Modern.Boursar.UI.GeneralCommand,Tosan.Modern.Boursar.UI",
    "PresenterName": null,
    "DefaultFilterQualifiedName": null,
    "IconName": null,
    "ObjectDefinition": null,
    "ModuleId": 67,
    "DisplayState": 0,
    "TransactionCode": null,
    "IsParametric": false,
    "ParentFilter": null,
    "ID": 650009,
    "Version": 0,
    "CreationDate": "2020-04-05T12:12:00.2359358+04:30",
    "LastChange": "2020-04-05T12:12:00.2359358+04:30",
    "Creator": "",
    "LastUpdater": ""
  },
  {
    "_iconSource": 0,
    "_title": null,
    "Name": "BrokerBlockedDepositReport",
    "Code": "650008",
    "CommandType": 6,
    "QualifiedName": "Tosan.Modern.Boursar.UI.GeneralCommand,Tosan.Modern.Boursar.UI",
    "PresenterName": null,
    "DefaultFilterQualifiedName": null,
    "IconName": null,
    "ObjectDefinition": null,
    "ModuleId": 67,
    "DisplayState": 0,
    "TransactionCode": null,
    "IsParametric": false,
    "ParentFilter": null,
    "ID": 650008,
    "Version": 0,
    "CreationDate": "2020-04-05T12:12:00.2359358+04:30",
    "LastChange": "2020-04-05T12:12:00.2359358+04:30",
    "Creator": "",
    "LastUpdater": ""
  }
]
